xray.py
xarray/__init__.py
xarray/conventions.py
xarray/convert.py
xarray/tutorial.py
xarray/ufuncs.py
xarray/version.py
xarray/backends/__init__.py
xarray/backends/api.py
xarray/backends/common.py
xarray/backends/h5netcdf_.py
xarray/backends/memory.py
xarray/backends/netCDF4_.py
xarray/backends/netcdf3.py
xarray/backends/pydap_.py
xarray/backends/pynio_.py
xarray/backends/scipy_.py
xarray/core/__init__.py
xarray/core/alignment.py
xarray/core/combine.py
xarray/core/common.py
xarray/core/coordinates.py
xarray/core/dataarray.py
xarray/core/dataset.py
xarray/core/formatting.py
xarray/core/groupby.py
xarray/core/indexing.py
xarray/core/merge.py
xarray/core/npcompat.py
xarray/core/nputils.py
xarray/core/ops.py
xarray/core/options.py
xarray/core/pycompat.py
xarray/core/utils.py
xarray/core/variable.py
xarray/plot/__init__.py
xarray/plot/default_colormap.csv
xarray/plot/facetgrid.py
xarray/plot/plot.py
xarray/plot/utils.py
xarray/test/__init__.py
xarray/test/test_backends.py
xarray/test/test_combine.py
xarray/test/test_conventions.py
xarray/test/test_dask.py
xarray/test/test_dataarray.py
xarray/test/test_dataset.py
xarray/test/test_formatting.py
xarray/test/test_indexing.py
xarray/test/test_ops.py
xarray/test/test_plot.py
xarray/test/test_tutorial.py
xarray/test/test_ufuncs.py
xarray/test/test_utils.py
xarray/test/test_variable.py
xarray/test/test_xray.py
xarray/test/data/bears.nc
xarray/test/data/example_1.nc
xarray/test/data/example_1.nc.gz
xray-0.7.0.dist-info/DESCRIPTION.rst
xray-0.7.0.dist-info/METADATA
xray-0.7.0.dist-info/RECORD
xray-0.7.0.dist-info/WHEEL
xray-0.7.0.dist-info/metadata.json
xray-0.7.0.dist-info/top_level.txt
