Metadata-Version: 2.0
Name: xray
Version: 0.7.0
Summary: N-D labeled arrays and datasets in Python
Home-page: https://github.com/pydata/xarray
Author: xarray Developers
Author-email: xarray@googlegroups.com
License: Apache
Platform: UNKNOWN
Classifier: Development Status :: 4 - Beta
Classifier: License :: OSI Approved :: Apache Software License
Classifier: Operating System :: OS Independent
Classifier: Intended Audience :: Science/Research
Classifier: Programming Language :: Python
Classifier: Programming Language :: Python :: 2
Classifier: Programming Language :: Python :: 2.6
Classifier: Programming Language :: Python :: 2.7
Classifier: Programming Language :: Python :: 3
Classifier: Programming Language :: Python :: 3.3
Classifier: Programming Language :: Python :: 3.4
Classifier: Programming Language :: Python :: 3.5
Classifier: Topic :: Scientific/Engineering
Requires-Dist: numpy (>=1.7)
Requires-Dist: pandas (>=0.15.0)
